dcmspec/__init__.py
dcmspec/apps/__init__.py
dcmspec/apps/cli/__init__.py
dcmspec/apps/cli/dataelements.py
dcmspec/apps/cli/iodattributes.py
dcmspec/apps/cli/iodmodules.py
dcmspec/apps/cli/modattributes.py
dcmspec/apps/cli/tdwiicontent.py
dcmspec/apps/cli/uidvalues.py
dcmspec/apps/cli/upsdimseattributes.py
dcmspec/apps/cli/upsioddimseattributes.py
dcmspec/apps/ui/iod_explorer/README.md
dcmspec/apps/ui/iod_explorer/__init__.py
dcmspec/apps/ui/iod_explorer/config/README.md
dcmspec/apps/ui/iod_explorer/config/iod_explorer_config.json
dcmspec/apps/ui/iod_explorer/config/iod_explorer_config_debug.json
dcmspec/apps/ui/iod_explorer/config/iod_explorer_config_example.json
dcmspec/apps/ui/iod_explorer/config/iod_explorer_config_minimal_logging.json
dcmspec/apps/ui/iod_explorer/iod_explorer.py
dcmspec/config.py
dcmspec/csv_table_spec_parser.py
dcmspec/doc_handler.py
dcmspec/dom_table_spec_parser.py
dcmspec/dom_utils.py
dcmspec/iod_spec_builder.py
dcmspec/iod_spec_printer.py
dcmspec/json_spec_store.py
dcmspec/module_registry.py
dcmspec/pdf_doc_handler.py
dcmspec/progress.py
dcmspec/service_attribute_defaults.py
dcmspec/service_attribute_model.py
dcmspec/spec_factory.py
dcmspec/spec_merger.py
dcmspec/spec_model.py
dcmspec/spec_parser.py
dcmspec/spec_printer.py
dcmspec/spec_store.py
dcmspec/ups_xhtml_doc_handler.py
dcmspec/xhtml_doc_handler.py
dcmspec-0.2.3.dist-info/METADATA
dcmspec-0.2.3.dist-info/WHEEL
dcmspec-0.2.3.dist-info/entry_points.txt
dcmspec-0.2.3.dist-info/licenses/LICENSE
dcmspec-0.2.3.dist-info/RECORD
