Metadata-Version: 2.4
Name: dcmspec
Version: 0.2.3
Summary: Toolkit for extracting, parsing, and processing DICOM specifications.
License: Apache-2.0
License-File: LICENSE
Keywords: DICOM,python
Author: David Wikler
Author-email: david.wikler@ulb.be
Requires-Python: >=3.10,<4.0
Classifier: Development Status :: 3 - Alpha
Classifier: Intended Audience :: Developers
Classifier: Intended Audience :: Healthcare Industry
Classifier: License :: OSI Approved :: Apache Software License
Classifier: Programming Language :: Python :: 3
Classifier: Programming Language :: Python :: 3.10
Classifier: Programming Language :: Python :: 3.11
Classifier: Programming Language :: Python :: 3.12
Classifier: Programming Language :: Python :: 3 :: Only
Classifier: Operating System :: OS Independent
Classifier: Topic :: Software Development :: Libraries
Classifier: Topic :: Scientific/Engineering :: Medical Science Apps.
Provides-Extra: gui
Provides-Extra: pdf
Requires-Dist: anytree (>=2.13.0,<3.0.0)
Requires-Dist: bs4 (>=0.0.2,<0.0.3)
Requires-Dist: camelot-py (>=1.0.0,<2.0.0) ; extra == "pdf"
Requires-Dist: lxml (>=5.4.0,<6.0.0)
Requires-Dist: opencv-python-headless (>=4.12.0.88,<5.0.0) ; extra == "pdf"
Requires-Dist: openpyxl (>=3.1.5,<4.0.0) ; extra == "pdf"
Requires-Dist: pandas (>=2.3.1,<3.0.0) ; extra == "pdf"
Requires-Dist: pdfplumber (>=0.11.7,<0.12.0) ; extra == "pdf"
Requires-Dist: platformdirs (>=4.3.8,<5.0.0)
Requires-Dist: requests (>=2.32.3,<3.0.0)
Requires-Dist: rich (>=14.0.0,<15.0.0)
Requires-Dist: tkhtmlview (>=0.3.1,<0.4.0) ; extra == "gui"
Requires-Dist: unidecode (>=1.4.0,<2.0.0)
Project-URL: Changelog, https://dwikler.github.io/dcmspec/changelog/
Project-URL: Documentation, https://dwikler.github.io/dcmspec/
Project-URL: Homepage, https://github.com/dwikler/dcmspec
Project-URL: Issues, https://github.com/dwikler/dcmspec/issues
Project-URL: Source, https://github.com/dwikler/dcmspec
